hirpa/__init__.py
hirpa/biz/__init__.py
hirpa/biz/agent/__init__.py
hirpa/biz/agent/tools/__init__.py
hirpa/biz/agent/tools/fn_code.py
hirpa/biz/agent/tools/fn_code_helper.py
hirpa/biz/agent/tools/fn_tool_base.py
hirpa/biz/agent/tools/simples/__init__.py
hirpa/biz/agent/tools/simples/fn_current_weather.py
hirpa/biz/agent/tools/simples/fn_return_in_args.py
hirpa/llm/__init__.py
hirpa/llm/message.py
hirpa/sdk/__init__.py
hirpa/sdk/airpa_base.py
hirpa/sdk/hirpa_file_server.py
hirpa/utils/__init__.py
hirpa/utils/result.py
hirpafnwheel-0.1.1.dist-info/METADATA
hirpafnwheel-0.1.1.dist-info/WHEEL
hirpafnwheel-0.1.1.dist-info/top_level.txt
hirpafnwheel-0.1.1.dist-info/RECORD
