Metadata-Version: 2.1
Name: hirpafnwheel
Version: 0.1.1
Summary: 用于编写hirpa中原子能里的脚手架，对应Hirpa引擎0.8.5以上版本
Home-page: http://airpa.asiainfo.com.cn
Author: AISware RPA Team
Author-email: airpa@asiainfo.com
Classifier: Programming Language :: Python :: 3
Classifier: License :: OSI Approved :: MIT License
Classifier: Operating System :: OS Independent
Requires-Python: >=3.10
Requires-Dist: pydantic==1.10.12
Requires-Dist: Requests==2.31.0
Requires-Dist: openpyxl==3.1.2
